odoo/addons/filmin_somconnexio/CHANGELOG.md
odoo/addons/filmin_somconnexio/README.rst
odoo/addons/filmin_somconnexio/__init__.py
odoo/addons/filmin_somconnexio/__manifest__.py
odoo/addons/filmin_somconnexio/data/product_category_technology_supplier_data.xml
odoo/addons/filmin_somconnexio/data/product_product.xml
odoo/addons/filmin_somconnexio/data/sale_subscription_template.xml
odoo/addons/filmin_somconnexio/data/service_supplier.xml
odoo/addons/filmin_somconnexio/data/service_technology_service_supplier.xml
odoo/addons/filmin_somconnexio/demo/contract.xml
odoo/addons/filmin_somconnexio/demo/stock_lot.xml
odoo/addons/filmin_somconnexio/i18n/ca_ES.po
odoo/addons/filmin_somconnexio/i18n/es.po
odoo/addons/filmin_somconnexio/listeners/__init__.py
odoo/addons/filmin_somconnexio/listeners/crm_lead_listener.py
odoo/addons/filmin_somconnexio/models/__init__.py
odoo/addons/filmin_somconnexio/models/contract_contract.py
odoo/addons/filmin_somconnexio/models/contract_line.py
odoo/addons/filmin_somconnexio/models/crm_lead.py
odoo/addons/filmin_somconnexio/models/crm_lead_line.py
odoo/addons/filmin_somconnexio/models/ir_server_action.py
odoo/addons/filmin_somconnexio/models/res_partner.py
odoo/addons/filmin_somconnexio/reports/crm_lead_creation_email_template.xml
odoo/addons/filmin_somconnexio/reports/crm_lead_creation_manual_email_template.xml
odoo/addons/filmin_somconnexio/tests/__init__.py
odoo/addons/filmin_somconnexio/tests/helper_service.py
odoo/addons/filmin_somconnexio/tests/listeners/__init__.py
odoo/addons/filmin_somconnexio/tests/listeners/test_crm_lead_listener.py
odoo/addons/filmin_somconnexio/tests/models/__init__.py
odoo/addons/filmin_somconnexio/tests/models/test_contract.py
odoo/addons/filmin_somconnexio/tests/models/test_contract_line.py
odoo/addons/filmin_somconnexio/tests/models/test_crm_lead.py
odoo/addons/filmin_somconnexio/tests/models/test_crm_lead_line.py
odoo/addons/filmin_somconnexio/tests/models/test_ir_server_action.py
odoo_addon_filmin_somconnexio-16.0.1.0.4.dist-info/METADATA
odoo_addon_filmin_somconnexio-16.0.1.0.4.dist-info/WHEEL
odoo_addon_filmin_somconnexio-16.0.1.0.4.dist-info/top_level.txt
odoo_addon_filmin_somconnexio-16.0.1.0.4.dist-info/RECORD
